plopp/__init__.py
plopp/py.typed
plopp/utils.py
plopp/backends/__init__.py
plopp/backends/common.py
plopp/backends/matplotlib/__init__.py
plopp/backends/matplotlib/canvas.py
plopp/backends/matplotlib/fast_image.py
plopp/backends/matplotlib/figure.py
plopp/backends/matplotlib/image.py
plopp/backends/matplotlib/line.py
plopp/backends/matplotlib/mesh_image.py
plopp/backends/matplotlib/scatter.py
plopp/backends/matplotlib/tiled.py
plopp/backends/matplotlib/utils.py
plopp/backends/plotly/__init__.py
plopp/backends/plotly/canvas.py
plopp/backends/plotly/figure.py
plopp/backends/plotly/line.py
plopp/backends/pythreejs/__init__.py
plopp/backends/pythreejs/canvas.py
plopp/backends/pythreejs/figure.py
plopp/backends/pythreejs/mesh3d.py
plopp/backends/pythreejs/outline.py
plopp/backends/pythreejs/scatter3d.py
plopp/core/__init__.py
plopp/core/__init__.pyi
plopp/core/graph.py
plopp/core/helpers.py
plopp/core/limits.py
plopp/core/node_class.py
plopp/core/typing.py
plopp/core/utils.py
plopp/core/view.py
plopp/data/__init__.py
plopp/data/examples.py
plopp/data/factory.py
plopp/data/testing.py
plopp/graphics/__init__.py
plopp/graphics/__init__.pyi
plopp/graphics/basefig.py
plopp/graphics/bbox.py
plopp/graphics/camera.py
plopp/graphics/colormapper.py
plopp/graphics/figures.py
plopp/graphics/graphicalview.py
plopp/graphics/tiled.py
plopp/plotting/__init__.py
plopp/plotting/__init__.pyi
plopp/plotting/common.py
plopp/plotting/inspector.py
plopp/plotting/mesh3d.py
plopp/plotting/plot.py
plopp/plotting/scatter.py
plopp/plotting/scatter3d.py
plopp/plotting/slicer.py
plopp/plotting/superplot.py
plopp/plotting/xyplot.py
plopp/widgets/__init__.py
plopp/widgets/__init__.pyi
plopp/widgets/box.py
plopp/widgets/checkboxes.py
plopp/widgets/clip3d.py
plopp/widgets/debounce.py
plopp/widgets/drawing.py
plopp/widgets/linesave.py
plopp/widgets/slice.py
plopp/widgets/style.py
plopp/widgets/toolbar.py
plopp/widgets/tools.py
plopp-25.9.0.dist-info/licenses/LICENSE
plopp-25.9.0.dist-info/METADATA
plopp-25.9.0.dist-info/WHEEL
plopp-25.9.0.dist-info/top_level.txt
plopp-25.9.0.dist-info/RECORD
